cfapackages/__init__.py
cfapackages/unpack.py
cfapackages_cfa-0.0.1.dist-info/LICENCE
cfapackages_cfa-0.0.1.dist-info/METADATA
cfapackages_cfa-0.0.1.dist-info/WHEEL
cfapackages_cfa-0.0.1.dist-info/top_level.txt
cfapackages_cfa-0.0.1.dist-info/RECORD
