Metadata-Version: 2.1
Name: cfapackages-cfa
Version: 0.0.1
Summary: Chick-fil-A packages
Home-page: https://github.com/pypa/sampleproject
Author: Omolewa Adaramola
Author-email: omolewa.davids@gmail.com
License: UNKNOWN
Platform: UNKNOWN
Classifier: Programming Language :: Python :: 3
Classifier: License :: OSI Approved :: MIT License
Classifier: Operating System :: OS Independent
Requires-Python: >=3.6
